pickemOdder/__init__.py
pickemOdder/cli.py
pickemOdder/getoddsdata.py
pickemOdder/pickemOdder.py
pickemOdder-1.0.2.dist-info/AUTHORS.rst
pickemOdder-1.0.2.dist-info/LICENSE
pickemOdder-1.0.2.dist-info/METADATA
pickemOdder-1.0.2.dist-info/WHEEL
pickemOdder-1.0.2.dist-info/entry_points.txt
pickemOdder-1.0.2.dist-info/top_level.txt
pickemOdder-1.0.2.dist-info/RECORD
