Metadata-Version: 2.1
Name: pickemOdder
Version: 1.0.2
Summary: Parse input game stats and output rank orderd picks
Home-page: https://github.com/danwald/pickemOdder
Author: danny crasto
Author-email: danwald79@gmail.com
License: MIT license
Keywords: pickemOdder
Platform: UNKNOWN
Classifier: Intended Audience :: Developers
Classifier: License :: OSI Approved :: MIT License
Classifier: Natural Language :: English
Classifier: Programming Language :: Python :: 3
Classifier: Programming Language :: Python :: 3.6
Classifier: Programming Language :: Python :: 3.7
Classifier: Programming Language :: Python :: 3.8
Requires-Python: >=3.6
Requires-Dist: pandas (==1.2.0)
Requires-Dist: requests (==2.25.1)
